contact_properties.py
hub_api.py
hubbypy/__init__.py
hubbypy/contact_properties.py
hubbypy/hub_api.py
hubbypy-0.1.8.dist-info/DESCRIPTION.rst
hubbypy-0.1.8.dist-info/LICENSE.txt
hubbypy-0.1.8.dist-info/METADATA
hubbypy-0.1.8.dist-info/RECORD
hubbypy-0.1.8.dist-info/WHEEL
hubbypy-0.1.8.dist-info/metadata.json
hubbypy-0.1.8.dist-info/top_level.txt
