Metadata-Version: 2.0
Name: hubbypy
Version: 0.1.8
Summary: A Python wrapper for the HubSpot contacts and contact properties API
Home-page: https://github.com/gojefferson/hubbypy
Author: Jeff Kerr
Author-email: jeff@casefleet.com
License: BSD
Platform: UNKNOWN
Classifier: Development Status :: 2 - Pre-Alpha
Classifier: Intended Audience :: Developers
Classifier: License :: OSI Approved :: BSD License
Classifier: Operating System :: OS Independent
Classifier: Programming Language :: Python
Classifier: Programming Language :: Python :: 3
Classifier: Programming Language :: Python :: 3.2
Classifier: Programming Language :: Python :: 3.3
Classifier: Programming Language :: Python :: 3.4
Classifier: Programming Language :: Python :: 3.5
Requires-Dist: requests
